dicergirl/hsr/__init__.py
dicergirl/hsr/hsrcards.py
dicergirl/hsr/nbhandlers.py
dicergirl/hsr/trailblazer.py
dicergirl_plugin_hsr-1.0.1.dist-info/METADATA
dicergirl_plugin_hsr-1.0.1.dist-info/WHEEL
dicergirl_plugin_hsr-1.0.1.dist-info/top_level.txt
dicergirl_plugin_hsr-1.0.1.dist-info/RECORD
